MANIFEST.in
README.md
development.ini
production.ini
setup.cfg
setup.py
clientMOE.egg-info/PKG-INFO
clientMOE.egg-info/SOURCES.txt
clientMOE.egg-info/dependency_links.txt
clientMOE.egg-info/not-zip-safe
clientMOE.egg-info/requires.txt
clientMOE.egg-info/top_level.txt
moe/__init__.py
moe/resources.py
moe/bandit/__init__.py
moe/bandit/bandit_interface.py
moe/bandit/constant.py
moe/bandit/data_containers.py
moe/bandit/linkers.py
moe/bandit/utils.py
moe/bandit/bla/__init__.py
moe/bandit/bla/bla.py
moe/bandit/epsilon/__init__.py
moe/bandit/epsilon/epsilon_first.py
moe/bandit/epsilon/epsilon_greedy.py
moe/bandit/epsilon/epsilon_interface.py
moe/bandit/ucb/__init__.py
moe/bandit/ucb/ucb1.py
moe/bandit/ucb/ucb1_tuned.py
moe/bandit/ucb/ucb_interface.py
moe/easy_interface/__init__.py
moe/easy_interface/bandit_simple_endpoint.py
moe/easy_interface/experiment.py
moe/easy_interface/simple_endpoint.py
moe/optimal_learning/__init__.py
moe/optimal_learning/python/__init__.py
moe/optimal_learning/python/comparison.py
moe/optimal_learning/python/constant.py
moe/optimal_learning/python/data_containers.py
moe/optimal_learning/python/geometry_utils.py
moe/optimal_learning/python/linkers.py
moe/optimal_learning/python/repeated_domain.py
moe/optimal_learning/python/timing.py
moe/optimal_learning/python/interfaces/__init__.py
moe/optimal_learning/python/interfaces/covariance_interface.py
moe/optimal_learning/python/interfaces/domain_interface.py
moe/optimal_learning/python/interfaces/expected_improvement_interface.py
moe/optimal_learning/python/interfaces/gaussian_process_interface.py
moe/optimal_learning/python/interfaces/log_likelihood_interface.py
moe/optimal_learning/python/interfaces/optimization_interface.py
moe/optimal_learning/python/python_version/__init__.py
moe/optimal_learning/python/python_version/covariance.py
moe/optimal_learning/python/python_version/domain.py
moe/optimal_learning/python/python_version/expected_improvement.py
moe/optimal_learning/python/python_version/gaussian_process.py
moe/optimal_learning/python/python_version/log_likelihood.py
moe/optimal_learning/python/python_version/optimization.py
moe/optimal_learning/python/python_version/python_utils.py
