Metadata-Version: 1.1
Name: clientMOE
Version: 0.1
Summary: Metric Optimization Engine
Home-page: https://github.com/Yelp/MOE
Author: Scott Clark and Eric Liu
Author-email: opensource+moe@yelp.com
License: UNKNOWN
Keywords: bayesian global optimization optimal learning expected improvement experiment design
Platform: UNKNOWN
Classifier: Development Status :: 4 - Beta
Classifier: Intended Audience :: Science/Research
Classifier: Intended Audience :: Developers
Classifier: Programming Language :: Python
Classifier: Topic :: Software Development
Classifier: Topic :: Scientific/Engineering
Classifier: Operating System :: Unix
Classifier: Operating System :: MacOS
